LICENSE.txt
README.rst
setup.cfg
setup.py
numtoname/__init__.py
numtoname/functions.py
numtoname/helpers.py
numtoname/tests.py
numtoname.egg-info/PKG-INFO
numtoname.egg-info/SOURCES.txt
numtoname.egg-info/dependency_links.txt
numtoname.egg-info/top_level.txt